pysub/__init__.py
pysub/subplots.py
pySubplots-1.2.2.dist-info/LICENSE
pySubplots-1.2.2.dist-info/METADATA
pySubplots-1.2.2.dist-info/WHEEL
pySubplots-1.2.2.dist-info/entry_points.txt
pySubplots-1.2.2.dist-info/top_level.txt
pySubplots-1.2.2.dist-info/RECORD
