Metadata-Version: 2.1
Name: pySubplots
Version: 1.2.2
Summary: A python script for plotting multiple subplots.
Home-page: https://github.com/kimariyb/py-subplots
Author: Kimariyb, Ryan Hsiun
Author-email: kimariyb@163.com
Classifier: Programming Language :: Python :: 3
Classifier: License :: OSI Approved :: MIT License
Classifier: Operating System :: OS Independent
Requires-Python: >=3.8
License-File: LICENSE
